singularity/__init__.py
singularity/data.py
singularity/singularity.py
singularitytechnologies.singularity_cli-0.2.5.dev0.dist-info/METADATA
singularitytechnologies.singularity_cli-0.2.5.dev0.dist-info/WHEEL
singularitytechnologies.singularity_cli-0.2.5.dev0.dist-info/entry_points.txt
singularitytechnologies.singularity_cli-0.2.5.dev0.dist-info/top_level.txt
singularitytechnologies.singularity_cli-0.2.5.dev0.dist-info/RECORD
