Metadata-Version: 2.1
Name: singularitytechnologies.singularity-cli
Version: 0.2.5.dev0
Summary: A CLI to run common singularity tasks.
Home-page: https://github.com/singularitydigitaltechnologies/singularity-cli
Author: Sam Lacey
Author-email: sam.lacey@singularity-technologies.io
License: MIT
Platform: UNKNOWN
Classifier: Programming Language :: Python :: 3
Classifier: License :: OSI Approved :: GNU General Public License v3 (GPLv3)
Classifier: Operating System :: OS Independent
Requires-Dist: asyncio
Requires-Dist: docopt
Requires-Dist: singularitytechnologies.singularitytechnologiesapi (==0.2.4dev)
